sentinel_value/__init__.py
sentinel_value/py.typed
sentinel_value/sentinel_value.py
sentinel_value-1.0.0.dist-info/LICENSE
sentinel_value-1.0.0.dist-info/WHEEL
sentinel_value-1.0.0.dist-info/METADATA
sentinel_value-1.0.0.dist-info/RECORD
