Metadata-Version: 2.1
Name: sentinel-value
Version: 1.0.0
Summary: Sentinel Values - unique objects akin to None, True, False
Home-page: https://github.com/vdmit11/sentinel-value
License: MIT
Keywords: sentinel,pep661,singleton,missing,util,typing
Author: Dmitry Vasilyanov
Author-email: vdmit11@gmail.com
Requires-Python: >=3.6.0,<4.0.0
Classifier: Development Status :: 4 - Beta
Classifier: Intended Audience :: Developers
Classifier: License :: OSI Approved :: MIT License
Classifier: Programming Language :: Python
Classifier: Programming Language :: Python :: 3
Classifier: Programming Language :: Python :: 3.10
Classifier: Programming Language :: Python :: 3.6
Classifier: Programming Language :: Python :: 3.7
Classifier: Programming Language :: Python :: 3.8
Classifier: Programming Language :: Python :: 3.9
Classifier: Topic :: Software Development :: Libraries
Classifier: Topic :: Software Development :: Libraries :: Python Modules
Project-URL: Documentation, https://sentinel-value.readthedocs.io
Project-URL: Repository, https://github.com/vdmit11/sentinel-value
